mcp_gaodeweather_server_zheng/__init__.py
mcp_gaodeweather_server_zheng/server.py
mcp_gaodeweather_server_zheng-0.1.0.dist-info/METADATA
mcp_gaodeweather_server_zheng-0.1.0.dist-info/WHEEL
mcp_gaodeweather_server_zheng-0.1.0.dist-info/entry_points.txt
mcp_gaodeweather_server_zheng-0.1.0.dist-info/RECORD
