Metadata-Version: 2.4
Name: mcp-gaodeweather-server-zheng
Version: 0.1.0
Summary: Add your description here
Requires-Python: >=3.11
Requires-Dist: mcp[cli]>=1.8.1
